{
  "level":"INFO",
  "message":"This is a GraphQL response.",
  "msgType":1,
  "source":"Test",
  "thread":"main",
  "timestamp":1400000000000000000,
  "version":1,
  "attachment":
  {
    "data":{
      "__schema":{
	"types":[
	  {
	    "name":"__EnumValue",
	    "fields":[
	      {
		"name":"name",
		"type":{
		  "name":"String!",
		  "kind":"NON_NULL",
		  "ofType":{
		    "name":"String",
		    "kind":"SCALAR"
		  }
		}
	      },
	      {
		"name":"description",
		"type":{
		  "name":"String",
		  "kind":"SCALAR",
		  "ofType":null
		}
	      },
	      {
		"name":"isDeprecated",
		"type":{
		  "name":"Boolean!",
		  "kind":"NON_NULL",
		  "ofType":{
		    "name":"Boolean",
		    "kind":"SCALAR"
		  }
		}
	      },
	      {
		"name":"deprecationReason",
		"type":{
		  "name":"String",
		  "kind":"SCALAR",
		  "ofType":null
		}
	      }
	    ]
	  },
	  {
	    "name":"Int",
	    "fields":null
	  },
	  {
	    "name":"I64",
	    "fields":null
	  },
	  {
	    "name":"__DirectiveLocation",
	    "fields":null
	  },
	  {
	    "name":"Time",
	    "fields":null
	  },
	  {
	    "name":"__Schema",
	    "fields":[
	      {
		"name":"types",
		"type":{
		  "name":"[__Type!]!",
		  "kind":"NON_NULL",
		  "ofType":{
		    "name":"[__Type!]",
		    "kind":"LIST"
		  }
		}
	      },
	      {
		"name":"queryType",
		"type":{
		  "name":"__Type!",
		  "kind":"NON_NULL",
		  "ofType":{
		    "name":"__Type",
		    "kind":"OBJECT"
		  }
		}
	      },
	      {
		"name":"mutationType",
		"type":{
		  "name":"__Type",
		  "kind":"OBJECT",
		  "ofType":null
		}
	      },
	      {
		"name":"subscriptionType",
		"type":{
		  "name":"__Type",
		  "kind":"OBJECT",
		  "ofType":null
		}
	      },
	      {
		"name":"directives",
		"type":{
		  "name":"[__Directive!]!",
		  "kind":"NON_NULL",
		  "ofType":{
		    "name":"[__Directive!]",
		    "kind":"LIST"
		  }
		}
	      }
	    ]
	  },
	  {
	    "name":"Mutation",
	    "fields":[
	      {
		"name":"like",
		"type":{
		  "name":"Song",
		  "kind":"OBJECT",
		  "ofType":null
		}
	      }
	    ]
	  },
	  {
	    "name":"Date",
	    "fields":null
	  },
	  {
	    "name":"Uuid",
	    "fields":null
	  },
	  {
	    "name":"Boolean",
	    "fields":null
	  },
	  {
	    "name":"String",
	    "fields":null
	  },
	  {
	    "name":"Song",
	    "fields":[
	      {
		"name":"name",
		"type":{
		  "name":"String!",
		  "kind":"NON_NULL",
		  "ofType":{
		    "name":"String",
		    "kind":"SCALAR"
		  }
		}
	      },
	      {
		"name":"artist",
		"type":{
		  "name":"Artist",
		  "kind":"OBJECT",
		  "ofType":null
		}
	      },
	      {
		"name":"duration",
		"type":{
		  "name":"Int",
		  "kind":"SCALAR",
		  "ofType":null
		}
	      },
	      {
		"name":"release",
		"type":{
		  "name":"Date",
		  "kind":"SCALAR",
		  "ofType":null
		}
	      },
	      {
		"name":"likes",
		"type":{
		  "name":"Int",
		  "kind":"SCALAR",
		  "ofType":null
		}
	      }
	    ]
	  },
	  {
	    "name":"ID",
	    "fields":null
	  },
	  {
	    "name":"Artist",
	    "fields":[
	      {
		"name":"name",
		"type":{
		  "name":"String!",
		  "kind":"NON_NULL",
		  "ofType":{
		    "name":"String",
		    "kind":"SCALAR"
		  }
		}
	      },
	      {
		"name":"songs",
		"type":{
		  "name":"[Song]",
		  "kind":"LIST",
		  "ofType":{
		    "name":"Song",
		    "kind":"OBJECT"
		  }
		}
	      },
	      {
		"name":"origin",
		"type":{
		  "name":"[String]",
		  "kind":"LIST",
		  "ofType":{
		    "name":"String",
		    "kind":"SCALAR"
		  }
		}
	      }
	    ]
	  },
	  {
	    "name":"__Directive",
	    "fields":[
	      {
		"name":"name",
		"type":{
		  "name":"String!",
		  "kind":"NON_NULL",
		  "ofType":{
		    "name":"String",
		    "kind":"SCALAR"
		  }
		}
	      },
	      {
		"name":"description",
		"type":{
		  "name":"String",
		  "kind":"SCALAR",
		  "ofType":null
		}
	      },
	      {
		"name":"locations",
		"type":{
		  "name":"[__DirectiveLocation!]!",
		  "kind":"NON_NULL",
		  "ofType":{
		    "name":"[__DirectiveLocation!]",
		    "kind":"LIST"
		  }
		}
	      },
	      {
		"name":"args",
		"type":{
		  "name":"[__InputValue!]!",
		  "kind":"NON_NULL",
		  "ofType":{
		    "name":"[__InputValue!]",
		    "kind":"LIST"
		  }
		}
	      }
	    ]
	  },
	  {
	    "name":"__Field",
	    "fields":[
	      {
		"name":"name",
		"type":{
		  "name":"String!",
		  "kind":"NON_NULL",
		  "ofType":{
		    "name":"String",
		    "kind":"SCALAR"
		  }
		}
	      },
	      {
		"name":"description",
		"type":{
		  "name":"String",
		  "kind":"SCALAR",
		  "ofType":null
		}
	      },
	      {
		"name":"args",
		"type":{
		  "name":"[__InputValue!]!",
		  "kind":"NON_NULL",
		  "ofType":{
		    "name":"[__InputValue!]",
		    "kind":"LIST"
		  }
		}
	      },
	      {
		"name":"type",
		"type":{
		  "name":"__Type!",
		  "kind":"NON_NULL",
		  "ofType":{
		    "name":"__Type",
		    "kind":"OBJECT"
		  }
		}
	      },
	      {
		"name":"isDeprecated",
		"type":{
		  "name":"Boolean!",
		  "kind":"NON_NULL",
		  "ofType":{
		    "name":"Boolean",
		    "kind":"SCALAR"
		  }
		}
	      },
	      {
		"name":"deprecationReason",
		"type":{
		  "name":"String",
		  "kind":"SCALAR",
		  "ofType":null
		}
	      }
	    ]
	  },
	  {
	    "name":"__TypeKind",
	    "fields":null
	  },
	  {
	    "name":"Query",
	    "fields":[
	      {
		"name":"artist",
		"type":{
		  "name":"Artist",
		  "kind":"OBJECT",
		  "ofType":null
		}
	      },
	      {
		"name":"artists",
		"type":{
		  "name":"[Artist]",
		  "kind":"LIST",
		  "ofType":{
		    "name":"Artist",
		    "kind":"OBJECT"
		  }
		}
	      }
	    ]
	  },
	  {
	    "name":"__InputValue",
	    "fields":[
	      {
		"name":"name",
		"type":{
		  "name":"String!",
		  "kind":"NON_NULL",
		  "ofType":{
		    "name":"String",
		    "kind":"SCALAR"
		  }
		}
	      },
	      {
		"name":"description",
		"type":{
		  "name":"String",
		  "kind":"SCALAR",
		  "ofType":null
		}
	      },
	      {
		"name":"type",
		"type":{
		  "name":"__Type!",
		  "kind":"NON_NULL",
		  "ofType":{
		    "name":"__Type",
		    "kind":"OBJECT"
		  }
		}
	      },
	      {
		"name":"defaultValue",
		"type":{
		  "name":"String",
		  "kind":"SCALAR",
		  "ofType":null
		}
	      }
	    ]
	  },
	  {
	    "name":"__Type",
	    "fields":[
	      {
		"name":"kind",
		"type":{
		  "name":"__TypeKind!",
		  "kind":"NON_NULL",
		  "ofType":{
		    "name":"__TypeKind",
		    "kind":"ENUM"
		  }
		}
	      },
	      {
		"name":"name",
		"type":{
		  "name":"String",
		  "kind":"SCALAR",
		  "ofType":null
		}
	      },
	      {
		"name":"description",
		"type":{
		  "name":"String",
		  "kind":"SCALAR",
		  "ofType":null
		}
	      },
	      {
		"name":"fields",
		"type":{
		  "name":"[__Field!]",
		  "kind":"LIST",
		  "ofType":{
		    "name":"__Field!",
		    "kind":"NON_NULL"
		  }
		}
	      },
	      {
		"name":"interfaces",
		"type":{
		  "name":"[__Type!]",
		  "kind":"LIST",
		  "ofType":{
		    "name":"__Type!",
		    "kind":"NON_NULL"
		  }
		}
	      },
	      {
		"name":"possibleTypes",
		"type":{
		  "name":"[__Type!]",
		  "kind":"LIST",
		  "ofType":{
		    "name":"__Type!",
		    "kind":"NON_NULL"
		  }
		}
	      },
	      {
		"name":"enumValues",
		"type":{
		  "name":"[__EnumValue!]",
		  "kind":"LIST",
		  "ofType":{
		    "name":"__EnumValue!",
		    "kind":"NON_NULL"
		  }
		}
	      },
	      {
		"name":"inputFields",
		"type":{
		  "name":"[__InputValue!]",
		  "kind":"LIST",
		  "ofType":{
		    "name":"__InputValue!",
		    "kind":"NON_NULL"
		  }
		}
	      },
	      {
		"name":"ofType",
		"type":{
		  "name":"__Type",
		  "kind":"OBJECT",
		  "ofType":null
		}
	      }
	    ]
	  },
	  {
	    "name":"Float",
	    "fields":null
	  }
	]
      }
    }
  }
}
